COPYING
README.txt
requirements.txt
setup.py
obadmin/__init__.py
obadmin/pavement.py
obadmin/skel.py
obadmin/testrunner.py
obadmin.egg-info/PKG-INFO
obadmin.egg-info/SOURCES.txt
obadmin.egg-info/dependency_links.txt
obadmin.egg-info/entry_points.txt
obadmin.egg-info/requires.txt
obadmin.egg-info/top_level.txt
obadmin/admin/__init__.py
obadmin/admin/forms.py
obadmin/admin/models.py
obadmin/admin/sites.py
obadmin/admin/tasks.py
obadmin/admin/tests.py
obadmin/admin/urls.py
obadmin/admin/views.py
obadmin/admin/templates/admin/base_site.html
obadmin/admin/templates/admin/db/location/change_form.html
obadmin/admin/templates/admin/db/location/change_list.html
obadmin/admin/templates/admin/db/newsitem/change_list.html
obadmin/admin/templates/admin/streets/block/change_list.html
obadmin/admin/templates/obadmin/add_blob_seed.html
obadmin/admin/templates/obadmin/blob_seed_list.html
obadmin/admin/templates/obadmin/edit_schema.html
obadmin/admin/templates/obadmin/edit_schema_lookups.html
obadmin/admin/templates/obadmin/geocoder_success_rates.html
obadmin/admin/templates/obadmin/import_news.html
obadmin/admin/templates/obadmin/index.html
obadmin/admin/templates/obadmin/jobs_status.html
obadmin/admin/templates/obadmin/news_item_detail.html
obadmin/admin/templates/obadmin/old_base.html
obadmin/admin/templates/obadmin/schema_list.html
obadmin/admin/templates/obadmin/schemafield_list.html
obadmin/admin/templates/obadmin/scraper_history_list.html
obadmin/admin/templates/obadmin/scraper_history_schema.html
obadmin/admin/templates/obadmin/block/import_blocks.html
obadmin/admin/templates/obadmin/location/import_zip_shapefiles.html
obadmin/admin/templates/obadmin/location/pick_shapefile_layer.html
obadmin/admin/templates/obadmin/location/upload_shapefile.html
obadmin/project_templates/openblock/setup.py_tmpl
obadmin/project_templates/openblock/+project+/README.txt_tmpl
obadmin/project_templates/openblock/+project+/__init__.py
obadmin/project_templates/openblock/+project+/manage.py
obadmin/project_templates/openblock/+project+/manage.sh
obadmin/project_templates/openblock/+project+/models.py
obadmin/project_templates/openblock/+project+/settings.py_tmpl
